{
    "مواقع ذات صلة" : [
        {
            "title" : "وزارة الموارد البشرية والتنمية الاجتماعية",
            "to" : "/"
        },
        {
            "title" : "موقع الخير الشامل",
            "to" : "/"
        },
        {
            "title" : "المركز الدولي للأبحاث والدراسات",
            "to" : "/"
        },
        {
            "title" : "مكتبة العمل الخيري",
            "to" : "/"
        },
        {
            "title" : "المجلس التنسيقي للجمعيات بجازان",
            "to" : "/"
        }
    ],

    "سياسة بدار" : [
        {
            "title" : "سياسة إدارة المتطوعين",
            "to" : "/"
        },
        {
            "title" : "سياسة الإبلاغ عن المخالفات وحماية مقدمي البلاغات",
            "to" : "/"
        },
        {
            "title" : "سياسة الاحتفاظ بالوثائق وإتلافها",
            "to" : "/"
        },
        {
            "title" : "سياسة تعارض المصالح",
            "to" : "/"
        },
        {
            "title" : "سياسة تنظيم العلاقة مع المستفيدين وتقديم الخدمات",
            "to" : "/"
        },
        {
            "title" : "سياسة جمع التبرعات",
            "to" : "/"
        },
        {
            "title" : "سياسة خصوصية البيانات",
            "to" : "/"
        }
    ],

    "رابط" : [
        {
            "title" : "الرئيسية",
            "to" : "/"
        },
        {
            "title" : "من نحن",
            "to" : "/"
        },
        {
            "title" : "المكتبة",
            "to" : "/"
        },
        {
            "title" : "مبادراتنا",
            "to" : "/"
        },
        {
            "title" : "استثمر معنا",
            "to" : "/"
        },
        {
            "title" : "انضم إلينا",
            "to" : "/"
        },
        {
            "title" : "تواصل معنا",
            "to" : "/"
        }
    ]
}